py_ts_interfaces/__init__.py
py_ts_interfaces/cli.py
py_ts_interfaces/parser.py
py_ts_interfaces/py.typed
py_ts_interfaces/tests/__init__.py
py_ts_interfaces/tests/tests.py
py_ts_interfaces/tests/utils.py
py_ts_interfaces-0.5.0.dist-info/entry_points.txt
py_ts_interfaces-0.5.0.dist-info/LICENSE
py_ts_interfaces-0.5.0.dist-info/WHEEL
py_ts_interfaces-0.5.0.dist-info/METADATA
py_ts_interfaces-0.5.0.dist-info/RECORD
