Metadata-Version: 2.1
Name: py-ts-interfaces
Version: 0.5.0
Summary: A library that converts Python dataclasses with type annotations to a TypeScript interface and serializes them to a file.
Home-page: https://github.com/cs-cordero/py-ts-interfaces
License: MIT
Keywords: python,typescript,interfaces
Author: Christopher Cordero
Author-email: ccordero@protonmail.com
Requires-Python: >=3.7.2,<4.0.0
Classifier: License :: OSI Approved :: MIT License
Classifier: Operating System :: OS Independent
Classifier: Programming Language :: Python
Classifier: Programming Language :: Python :: 3
Classifier: Programming Language :: Python :: 3 :: Only
Classifier: Programming Language :: Python :: 3.10
Classifier: Programming Language :: Python :: 3.7
Classifier: Programming Language :: Python :: 3.8
Classifier: Programming Language :: Python :: 3.9
Classifier: Typing :: Typed
Requires-Dist: astroid (==2.14.2)
Project-URL: Documentation, https://github.com/cs-cordero/py-ts-interfaces
Project-URL: Repository, https://github.com/cs-cordero/py-ts-interfaces
